physarum/__init__.py
physarum-0.1.dist-info/LICENSE.txt
physarum-0.1.dist-info/METADATA
physarum-0.1.dist-info/WHEEL
physarum-0.1.dist-info/top_level.txt
physarum-0.1.dist-info/RECORD
