Metadata-Version: 2.1
Name: physarum
Version: 0.1
Summary: Simulate interacting physarum populations.
Home-page: https://github.com/MNoichl/physarum
Author: Maximilian Noichl
Author-email: noichlmax@hotmail.co.uk
License: MIT
Platform: UNKNOWN
Classifier: Programming Language :: Python :: 3
Classifier: License :: OSI Approved :: MIT License
Classifier: Operating System :: OS Independent
Requires-Python: >=3.6
